MK_SSL/__init__.py
MK_SSL/audio/Trainer.py
MK_SSL/audio/__init__.py
MK_SSL/audio/models/__init__.py
MK_SSL/audio/models/cola.py
MK_SSL/audio/models/eat.py
MK_SSL/audio/models/hubert.py
MK_SSL/audio/models/simclr.py
MK_SSL/audio/models/wav2vec2.py
MK_SSL/audio/models/modules/__init__.py
MK_SSL/audio/models/modules/backbones.py
MK_SSL/audio/models/modules/cola_backbone.py
MK_SSL/audio/models/modules/decoders.py
MK_SSL/audio/models/modules/eat_backbone.py
MK_SSL/audio/models/modules/feature_extractors.py
MK_SSL/audio/models/modules/heads.py
MK_SSL/audio/models/modules/hubert_backbone.py
MK_SSL/audio/models/modules/quantizer.py
MK_SSL/audio/models/modules/simclr_backbone.py
MK_SSL/audio/models/modules/wav2vec2_backbone.py
MK_SSL/audio/models/modules/losses/NTXent_loss.py
MK_SSL/audio/models/modules/losses/__init__.py
MK_SSL/audio/models/modules/losses/hubert_loss.py
MK_SSL/audio/models/modules/losses/infoNCE_loss.py
MK_SSL/audio/models/modules/losses/ufo_loss.py
MK_SSL/audio/models/modules/losses/wav2vec2_loss.py
MK_SSL/audio/models/modules/tools/__init__.py
MK_SSL/audio/models/modules/tools/pseudo_label_generator.py
MK_SSL/audio/models/modules/transformations/__init__.py
MK_SSL/audio/models/modules/transformations/cola_transform.py
MK_SSL/audio/models/modules/transformations/eat_transform.py
MK_SSL/audio/models/modules/transformations/simclr_transform.py
MK_SSL/audio/models/utils/__init__.py
MK_SSL/audio/models/utils/base_masking.py
MK_SSL/audio/models/utils/datasets.py
MK_SSL/audio/models/utils/evaluate.py
MK_SSL/audio/models/utils/registry.py
MK_SSL/graph/Trainer.py
MK_SSL/graph/__init__.py
MK_SSL/graph/models/__init__.py
MK_SSL/graph/models/graphcl.py
MK_SSL/graph/models/modules/__init__.py
MK_SSL/graph/models/modules/backbones.py
MK_SSL/graph/models/modules/heads.py
MK_SSL/graph/models/modules/losses/__init__.py
MK_SSL/graph/models/modules/losses/graphcl_loss.py
MK_SSL/graph/models/modules/transformations/__init__.py
mk_ssl-0.1.4.dist-info/licenses/LICENSE
mk_ssl-0.1.4.dist-info/METADATA
mk_ssl-0.1.4.dist-info/WHEEL
mk_ssl-0.1.4.dist-info/top_level.txt
mk_ssl-0.1.4.dist-info/RECORD
