Metadata-Version: 2.4
Name: mk-ssl
Version: 0.1.4
Summary: A Self-Supervised Learning Library
Author: Melika Shirian
Author-email: Kianoosh Vadaei <kia.vadaei@gmail.com>
License: MIT License
Project-URL: Homepage, https://github.com/MK-SSL-Lab/mk-unified-ssl-toolbox
Project-URL: Repository, https://github.com/MK-SSL-Lab/mk-unified-ssl-toolbox
Project-URL: Issues, https://github.com/MK-SSL-Lab/mk-unified-ssl-toolbox/issues
Classifier: Development Status :: 3 - Alpha
Classifier: Intended Audience :: Science/Research
Classifier: Intended Audience :: Education
Classifier: License :: OSI Approved :: MIT License
Classifier: Programming Language :: Python :: 3
Classifier: Programming Language :: Python :: 3.10
Classifier: Programming Language :: Python :: 3.11
Classifier: Topic :: Scientific/Engineering :: Artificial Intelligence
Classifier: Topic :: Software Development :: Libraries :: Python Modules
Requires-Python: >=3.10
License-File: LICENSE
Requires-Dist: axial_positional_embedding
Requires-Dist: colorlog
Requires-Dist: editdistance
Requires-Dist: einops
Requires-Dist: huggingface_hub
Requires-Dist: jiwer
Requires-Dist: joblib
Requires-Dist: numpy
Requires-Dist: opencv-python
Requires-Dist: optuna
Requires-Dist: pandas
Requires-Dist: peft
Requires-Dist: Pillow
Requires-Dist: plotly
Requires-Dist: scikit-learn
Requires-Dist: torch
Requires-Dist: torch_geometric
Requires-Dist: torchaudio
Requires-Dist: torcheval
Requires-Dist: torchmetrics
Requires-Dist: torchvision
Requires-Dist: tqdm
Requires-Dist: transformers
Requires-Dist: wandb
Provides-Extra: dev
Requires-Dist: pytest; extra == "dev"
Requires-Dist: black; extra == "dev"
Requires-Dist: ruff; extra == "dev"
Requires-Dist: mypy; extra == "dev"
Dynamic: license-file
Dynamic: requires-python
